hmm_write/__init__.py
hmm_write/hmm.py
hmm_write-0.3.4.dist-info/LICENSE
hmm_write-0.3.4.dist-info/METADATA
hmm_write-0.3.4.dist-info/WHEEL
hmm_write-0.3.4.dist-info/top_level.txt
hmm_write-0.3.4.dist-info/RECORD
