Metadata-Version: 2.1
Name: hmm-write
Version: 0.3.4
Summary: Python implementation of a Hidden Markov Machine that generates text.
Author: Toby Connor-Kebbell
License: UNKNOWN
Platform: UNKNOWN
Classifier: Programming Language :: Python :: 3
Classifier: License :: OSI Approved :: MIT License
Classifier: Operating System :: OS Independent
License-File: LICENSE
